{
  "name": "Derek Williams",
  "age": 33,
  "address": {
    "street": "Ufga Lane",
    "city": "Rigojcu",
    "state": "FL",
    "zip": "06588"
  },
  "contact": {
    "phone": "(620) 308-8275",
    "servicePhone": "800963545"
  },
  "birthday": "1985-05-29T06:17:34.845Z",
  "ip": "236.179.162.8",
  "foo": "bar",
  "profile": {
    "about": "Bez dajciz dofos cutussoz cefokmot lomi da mib lev kucur ira viva timane mawedrib rappimku. Umolait vem hu pi comkasu wi oh huataw ho duwoze bolkuhem zicuwug beva. Uvibe denanum div zolu mit kebsevip fudli kihot ocnam ketrumus tatniwzim kaov. Dozef illij gadco niipoloj sirab dajut div zi afinib nuzohma jokari fuw licenca. Mo nanzepnup finsog sammagiz kinuuk mi busipver suh doj ziceso gewelak emza uvepu. Tanfiz hub gozona orenruf go jovevuho egaidini uh ab favko lurdi usewawlo ewakedme deduc imo. Puviz megto do jawop ipodelfer oh reconbum ze ukbuali wodtoh elozizup wudakpor tos fan didzi iskatsej mueva.",
    "bio": "Bi uvpomak iwo rune ankelina ceuhvon cig veti as tebtieg rurjibce nejocid ru sik raz cus. Hel inuulmu okusned cicrece iju ifeazron zap dage jof ugeujijow ujjofoz azeze. Uzu jakviji bovtow ci mouc jap wugo malmif su hiviju ga buanipo nogujani ele taspic fa wispo nafjofsab."
  },
  "apiKey": "06428d7b98421d09e9bc41b302fe7a779b18a5dddd65f8972fd92bc231bb6663",
  "currency": {
    "code": "UYU",
    "name": "Uruguay Peso"
  }
}