{
  "name": "Vincent Hammond",
  "age": 33,
  "address": {
    "street": "Deon Center",
    "city": "Fewlujte",
    "state": "NC",
    "zip": "53449"
  },
  "contact": {
    "phone": "(848) 565-3494",
    "servicePhone": "800829513"
  },
  "birthday": "2006-06-20T09:37:07.929Z",
  "ip": "252.34.234.160",
  "foo": "bar",
  "profile": {
    "about": "Mabten buterin cehdeka jeuwdo furwaspak cav nidugob odicuvow caosu tig fecwi sibcakrog wanneg ah hip ha va. Cid joli go kezun hiis rekgaslu hoil wofihe bi ef idihevuz olipuj nela ifwu. Korvawo adolahow liwuszo kipuc gezvofoj zegucol didokano wo niig gek zulkigzav mo or unug. Ek ipoho hi fianbe bot miptobe zu olefa se ofpom ravosa gehiga. Igo ziosoic zeg berzolkup huinepu coho raal za di enwo evavu iwgot.",
    "bio": "Bi zo ruperuv saeceut ikorituz biokagu je duwjeko nomuklen waddiwpu tuozi fikjeati vol ri rimkifwob ivsep esihi ko. Atede ce kam dohotnu vuro lebet fumovom fel uv tujov tobazigiv ivhi bukozo mimza. Jouw tar keiw sijunve miffere ibo cawalaf wowig mejildew im lucjidmeh kumsaot vawera vucegsuj gave."
  },
  "apiKey": "8fa400b12a3c2c28b7733d0ccf488d7ff36c4655ebacaa9174de2a5daa36f0ee",
  "currency": {
    "code": "AED",
    "name": "United Arab Emirates Dirham"
  }
}