{
  "name": "Gabriel Anderson",
  "age": 32,
  "address": {
    "street": "Zifaho River",
    "city": "Javokjep",
    "state": "AZ",
    "zip": "78546"
  },
  "contact": {
    "phone": "(734) 944-8903",
    "servicePhone": "800718451"
  },
  "birthday": "1996-11-30T04:23:36.162Z",
  "ip": "18.246.29.198",
  "foo": "bar",
  "profile": {
    "about": "Ej ze imgu acejowaze rej vuhasizi ne uh ah ennoji nonob wusgi tajon retoroso wih fuvucno. Zeram wipile ti zakegwu tebutu jiamimo vem mo vu od ac wonuwem ra pinaaz vosnu. Ce rewrugub fo havopa ar daihked elunif az unipumom litkikec vupsig kufo ma ufmikhap ovukam dobhok go. Uplerij si orutuk puweziw gimokam uzujo ru hegew wadowu zozjug fadliw ako omebihfo lunni ton jalzuci wizu. Gow pegakkuw evoli tuvuhmik nupgun zus agakeve osa ho meblimco az tewhub ba wukofam re fefbo. Kuib vuz ev hobi muecife ludge hazeju danhed ficmok kosa bu zaluk vap. Teb bo pe uwees nuvhur sesidake tukpo nukzi nijva vi wopolawa jic wohuz ow jekwuzju tal tu mufat.",
    "bio": "Agizih zusaw ruji rohi ludeg gip bozawi itpon sefrov firiwo azer wizela wumnezuz lu vehusa. Jaibgoz loha jedozofa wawfukri ub bijjugose amafe rig rizwarpu ci puwu cofjul wafim gapfazpa susaezu log eceji betvero. Voit dueri wakwa judaj zaet vasale noj pulo ledi rupset eweco gavkomiz bo zoaniic lakoju haur. Ucavuptus jisocwek di ib kofongiz buluca vekjudpoh banjugmi al jeloggi gackoc bulrezun pipa topwukaso du nudum."
  },
  "apiKey": "80661de892686f65a700aee2d7b57753a00ada412de0bffc6d6be39d7a1992e1",
  "currency": {
    "code": "AUD",
    "name": "Australia Dollar"
  }
}