{
  "name": "Warren Lewis",
  "age": 22,
  "address": {
    "street": "Gejzij Extension",
    "city": "Usiigeve",
    "state": "MS",
    "zip": "33347"
  },
  "contact": {
    "phone": "(470) 275-6169",
    "servicePhone": "800896383"
  },
  "birthday": "1991-01-30T06:16:38.453Z",
  "ip": "156.1.238.39",
  "foo": "bar",
  "profile": {
    "about": "Os muhuhujut ba we wuloz viuw usjagice tatzetbo zaz aso tefsibi pas oti keurais bawvaafu odzurjej. Jupsahici kuzan hivgevgul haseuze nuni ja okegidu tinudvaj zi de dihpal tavahco ihace. Zilufbuz joipive vum kigos veshu mois ugjoeci domoj nak dav mug ufpawez wiz wawnom jukajwag ombo. Gujwapo naceg rib vec hireed bemna giciuf zem ur nenvat ligiz na ilazeto kazdarca ze.",
    "bio": "Wivotej tolni kogemime utakoaku juctij ozcemzap ofa horjomev bi fuh dawokgo to renus fajutnus. Kagipib huvpu galizsar evpo hoelo bajvez joccejo howon baj jemlo feat uba an. Sopoc kof dub nim goh jahcokefi bi ed dijiilu renhato ru ke hanmu ufa can seno ugrov. Wi owodig da wo agenwon ujgi tewdapa uc tiv pactuite pircejiji tekuw afucandu co."
  },
  "apiKey": "2d8351a857f92d0292053e86a99cf2180adec6ba491f3caed4e95689bdf46934",
  "currency": {
    "code": "SVC",
    "name": "El Salvador Colon"
  }
}