{
  "name": "Douglas Nash",
  "age": 19,
  "address": {
    "street": "Torveg Street",
    "city": "Afesgi",
    "state": "NV",
    "zip": "41259"
  },
  "contact": {
    "phone": "(426) 456-9734",
    "servicePhone": "800729285"
  },
  "birthday": "1988-12-27T10:19:20.478Z",
  "ip": "146.224.124.159",
  "foo": "bar",
  "profile": {
    "about": "Ucepogzis ebfavo bo diuremes gejamen puv tomkem tit gelkici ajoji buctuw ogtintaw geddu zecazrup vamtob muwaoci nuw zomset. Ahgace obi aj wakieb api urunun nij du vovput membus wec bi vozwod afo cehajho gif son kunu. Mir ralwog vaddapwi cefzi paz le huhsa vu ud fucfazin ju loru zewal dup eba divum. Eddofgus heg vap hu fucdilzob vepidta vu rirumfi reeci popidno ha piizsog co.",
    "bio": "Dugfatabu ev bore lednafer adaode nate samcobho uziimu vuv tow ohi huho ra rafu weto. Wi depkuw zatso wuofeeh tuk zo gi mimku awotik sunmile zaz ocuwofwo ivicowzoz taljowek wo obkakwot zikawfuc. Didlow ta icnu ac muz gubsus fuet bapveelo pe ewa ce comfi ocifi ceguvuku. Feih kaw joho ja zapo jo sazuj almocej vipida iv dawmonule jiw. Ad cuzgiblid geniwiz resazeme nigza igevew lowenin nu avuwu foviw mom ji. Hoazro cewene ov ki delca lupuk pavejhe kadba leru jijhag ka imtoggu."
  },
  "apiKey": "030843c5b48ca0713a27fe59d631f31ccf35a03f937a83b66ffdd2761f61e21d",
  "currency": {
    "code": "COP",
    "name": "Colombia Peso"
  }
}